[[0.123613,{"lines":{"0":[["Johns-MacBook-Pro 10:04:14 Dropbox  >                                   ",{}]],"1":[["                                                                        ",{}]],"2":[["                                                                        ",{}]],"3":[["                                                                        ",{}]],"4":[["                                                                        ",{}]],"5":[["                                                                        ",{}]],"6":[["                                                                        ",{}]],"7":[["                                                                        ",{}]],"8":[["                                                                        ",{}]],"9":[["                                                                        ",{}]],"10":[["                                                                        ",{}]],"11":[["                                                                        ",{}]],"12":[["                                                                        ",{}]],"13":[["                                                                        ",{}]],"14":[["                                                                        ",{}]],"15":[["                                                                        ",{}]],"16":[["                                                                        ",{}]],"17":[["                                                                        ",{}]],"18":[["                                                                        ",{}]],"19":[["                                                                        ",{}]],"20":[["                                                                        ",{}]],"21":[["                                                                        ",{}]]},"cursor":{"x":39,"y":0,"visible":true}}],[2.068526,{"lines":{"0":[["Johns-MacBook-Pro 10:04:14 Dropbox  >  c                                ",{}]]},"cursor":{"x":40}}],[0.423661,{"lines":{"0":[["Johns-MacBook-Pro 10:04:14 Dropbox  >  cd                               ",{}]]},"cursor":{"x":41}}],[0.416112,{"cursor":{"x":42}}],[0.599947,{"lines":{"0":[["Johns-MacBook-Pro 10:04:14 Dropbox  >  cd e                             ",{}]]},"cursor":{"x":43}}],[0.232092,{"lines":{"0":[["Johns-MacBook-Pro 10:04:14 Dropbox  >  cd ex                            ",{}]]},"cursor":{"x":44}}],[0.335941,{"lines":{"0":[["Johns-MacBook-Pro 10:04:14 Dropbox  >  cd example_test_directory/       ",{}]]},"cursor":{"x":65}}],[1.391861,{"cursor":{"x":0,"y":1}}],[0.00727,{"lines":{"1":[["Johns-MacBook-Pro 10:04:19 example_test_directory  >                    ",{}]]},"cursor":{"x":54}}],[0.664886,{"lines":{"1":[["Johns-MacBook-Pro 10:04:19 example_test_directory  >  l                 ",{}]]},"cursor":{"x":55}}],[0.287879,{"lines":{"1":[["Johns-MacBook-Pro 10:04:19 example_test_directory  >  ls                ",{}]]},"cursor":{"x":56}}],[0.263947,{"cursor":{"x":0,"y":2}}],[0.01258,{"lines":{"2":[["Icon? ",{}],["toolz",{"fg":4}],["                                                             ",{}]],"3":[["Johns-MacBook-Pro 10:04:20 example_test_directory  >                    ",{}]]},"cursor":{"x":54,"y":3}}],[5.603583,{"lines":{"3":[["Johns-MacBook-Pro 10:04:20 example_test_directory  >  #                 ",{}]]},"cursor":{"x":55}}],[0.279731,{"cursor":{"x":56}}],[1.656124,{"lines":{"3":[["Johns-MacBook-Pro 10:04:20 example_test_directory  >  # R               ",{}]]},"cursor":{"x":57}}],[0.192079,{"lines":{"3":[["Johns-MacBook-Pro 10:04:20 example_test_directory  >  # Re              ",{}]]},"cursor":{"x":58}}],[0.175918,{"lines":{"3":[["Johns-MacBook-Pro 10:04:20 example_test_directory  >  # Rec             ",{}]]},"cursor":{"x":59}}],[0.176019,{"lines":{"3":[["Johns-MacBook-Pro 10:04:20 example_test_directory  >  # Recu            ",{}]]},"cursor":{"x":60}}],[0.104024,{"lines":{"3":[["Johns-MacBook-Pro 10:04:20 example_test_directory  >  # Recul           ",{}]]},"cursor":{"x":61}}],[0.5278969999999999,{"lines":{"3":[["Johns-MacBook-Pro 10:04:20 example_test_directory  >  # Recu            ",{}]]},"cursor":{"x":60}}],[0.167882,{"lines":{"3":[["Johns-MacBook-Pro 10:04:20 example_test_directory  >  # Rec             ",{}]]},"cursor":{"x":59}}],[0.120081,{"lines":{"3":[["Johns-MacBook-Pro 10:04:20 example_test_directory  >  # Re              ",{}]]},"cursor":{"x":58}}],[0.08801299999999999,{"lines":{"3":[["Johns-MacBook-Pro 10:04:20 example_test_directory  >  # Reg             ",{}]]},"cursor":{"x":59}}],[0.160154,{"lines":{"3":[["Johns-MacBook-Pro 10:04:20 example_test_directory  >  # Regu            ",{}]]},"cursor":{"x":60}}],[0.055955,{"lines":{"3":[["Johns-MacBook-Pro 10:04:20 example_test_directory  >  # Regul           ",{}]]},"cursor":{"x":61}}],[0.215973,{"lines":{"3":[["Johns-MacBook-Pro 10:04:20 example_test_directory  >  # Regula          ",{}]]},"cursor":{"x":62}}],[0.040026,{"lines":{"3":[["Johns-MacBook-Pro 10:04:20 example_test_directory  >  # Regular         ",{}]]},"cursor":{"x":63}}],[0.127977,{"cursor":{"x":64}}],[0.151892,{"lines":{"3":[["Johns-MacBook-Pro 10:04:20 example_test_directory  >  # Regular t       ",{}]]},"cursor":{"x":65}}],[0.08008,{"lines":{"3":[["Johns-MacBook-Pro 10:04:20 example_test_directory  >  # Regular te      ",{}]]},"cursor":{"x":66}}],[0.039896,{"lines":{"3":[["Johns-MacBook-Pro 10:04:20 example_test_directory  >  # Regular tes     ",{}]]},"cursor":{"x":67}}],[0.088139,{"lines":{"3":[["Johns-MacBook-Pro 10:04:20 example_test_directory  >  # Regular test    ",{}]]},"cursor":{"x":68}}],[0.127887,{"lines":{"3":[["Johns-MacBook-Pro 10:04:20 example_test_directory  >  # Regular tests   ",{}]]},"cursor":{"x":69}}],[0.08812300000000001,{"cursor":{"x":70}}],[0.151983,{"lines":{"3":[["Johns-MacBook-Pro 10:04:20 example_test_directory  >  # Regular tests o ",{}]]},"cursor":{"x":71}}],[0.07997600000000001,{"lines":{"3":[["Johns-MacBook-Pro 10:04:20 example_test_directory  >  # Regular tests on",{}]]},"cursor":{"x":0,"y":4}}],[0.160044,{"lines":{"4":[["l                                                                       ",{}]]},"cursor":{"x":1}}],[0.079926,{"lines":{"4":[["ly                                                                      ",{}]]},"cursor":{"x":2}}],[1.071971,{"lines":{"4":[["ly:                                                                     ",{}]]},"cursor":{"x":3}}],[0.303949,{"cursor":{"x":0,"y":5}}],[0.005523,{"lines":{"5":[["Johns-MacBook-Pro 10:04:32 example_test_directory  >                    ",{}]]},"cursor":{"x":54}}],[2.803499,{"lines":{"5":[["Johns-MacBook-Pro 10:04:32 example_test_directory  >  n                 ",{}]]},"cursor":{"x":55}}],[0.055058,{"lines":{"5":[["Johns-MacBook-Pro 10:04:32 example_test_directory  >  no                ",{}]]},"cursor":{"x":56}}],[0.104012,{"lines":{"5":[["Johns-MacBook-Pro 10:04:32 example_test_directory  >  nos               ",{}]]},"cursor":{"x":57}}],[0.055822,{"lines":{"5":[["Johns-MacBook-Pro 10:04:32 example_test_directory  >  nose              ",{}]]},"cursor":{"x":58}}],[0.160155,{"lines":{"5":[["Johns-MacBook-Pro 10:04:32 example_test_directory  >  noset             ",{}]]},"cursor":{"x":59}}],[0.08,{"lines":{"5":[["Johns-MacBook-Pro 10:04:32 example_test_directory  >  nosete            ",{}]]},"cursor":{"x":60}}],[0.032136,{"lines":{"5":[["Johns-MacBook-Pro 10:04:32 example_test_directory  >  nosetes           ",{}]]},"cursor":{"x":61}}],[0.087837,{"lines":{"5":[["Johns-MacBook-Pro 10:04:32 example_test_directory  >  nosetest          ",{}]]},"cursor":{"x":62}}],[0.127998,{"lines":{"5":[["Johns-MacBook-Pro 10:04:32 example_test_directory  >  nosetests         ",{}]]},"cursor":{"x":63}}],[0.303779,{"cursor":{"x":0,"y":6}}],[0.133227,{"lines":{"6":[[".                                                                       ",{}]]},"cursor":{"x":1}}],[0.015092,{"lines":{"7":[["----------------------------------------------------------------------  ",{}]],"8":[["Ran 1 test in 0.002s                                                    ",{}]],"10":[["OK                                                                      ",{}]],"11":[["Johns-MacBook-Pro 10:04:36 example_test_directory  >                    ",{}]]},"cursor":{"x":54,"y":11}}],[1.755925,{"lines":{"11":[["Johns-MacBook-Pro 10:04:36 example_test_directory  >  #                 ",{}]]},"cursor":{"x":55}}],[0.143938,{"cursor":{"x":56}}],[0.215883,{"lines":{"11":[["Johns-MacBook-Pro 10:04:36 example_test_directory  >  # W               ",{}]]},"cursor":{"x":57}}],[0.392157,{"lines":{"11":[["Johns-MacBook-Pro 10:04:36 example_test_directory  >  # Wi              ",{}]]},"cursor":{"x":58}}],[0.159933,{"lines":{"11":[["Johns-MacBook-Pro 10:04:36 example_test_directory  >  # Wit             ",{}]]},"cursor":{"x":59}}],[0.040084,{"lines":{"11":[["Johns-MacBook-Pro 10:04:36 example_test_directory  >  # With            ",{}]]},"cursor":{"x":60}}],[0.135852,{"cursor":{"x":61}}],[0.224087,{"lines":{"11":[["Johns-MacBook-Pro 10:04:36 example_test_directory  >  # With d          ",{}]]},"cursor":{"x":62}}],[0.048084,{"lines":{"11":[["Johns-MacBook-Pro 10:04:36 example_test_directory  >  # With do         ",{}]]},"cursor":{"x":63}}],[0.095989,{"lines":{"11":[["Johns-MacBook-Pro 10:04:36 example_test_directory  >  # With doc        ",{}]]},"cursor":{"x":64}}],[0.255899,{"lines":{"11":[["Johns-MacBook-Pro 10:04:36 example_test_directory  >  # With doct       ",{}]]},"cursor":{"x":65}}],[0.088114,{"lines":{"11":[["Johns-MacBook-Pro 10:04:36 example_test_directory  >  # With docte      ",{}]]},"cursor":{"x":66}}],[0.08795799999999999,{"lines":{"11":[["Johns-MacBook-Pro 10:04:36 example_test_directory  >  # With doctes     ",{}]]},"cursor":{"x":67}}],[0.039926,{"lines":{"11":[["Johns-MacBook-Pro 10:04:36 example_test_directory  >  # With doctest    ",{}]]},"cursor":{"x":68}}],[0.128059,{"lines":{"11":[["Johns-MacBook-Pro 10:04:36 example_test_directory  >  # With doctests   ",{}]]},"cursor":{"x":69}}],[0.735999,{"lines":{"11":[["Johns-MacBook-Pro 10:04:36 example_test_directory  >  # With doctests:  ",{}]]},"cursor":{"x":70}}],[0.727893,{"cursor":{"x":0,"y":12}}],[0.008345999999999999,{"lines":{"12":[["Johns-MacBook-Pro 10:04:42 example_test_directory  >                    ",{}]]},"cursor":{"x":54}}],[0.616823,{"lines":{"12":[["Johns-MacBook-Pro 10:04:42 example_test_directory  >  n                 ",{}]]},"cursor":{"x":55}}],[0.06358,{"lines":{"12":[["Johns-MacBook-Pro 10:04:42 example_test_directory  >  no                ",{}]]},"cursor":{"x":56}}],[0.111669,{"lines":{"12":[["Johns-MacBook-Pro 10:04:42 example_test_directory  >  nos               ",{}]]},"cursor":{"x":57}}],[0.039885,{"lines":{"12":[["Johns-MacBook-Pro 10:04:42 example_test_directory  >  nose              ",{}]]},"cursor":{"x":58}}],[0.168264,{"lines":{"12":[["Johns-MacBook-Pro 10:04:42 example_test_directory  >  noset             ",{}]]},"cursor":{"x":59}}],[0.048235,{"lines":{"12":[["Johns-MacBook-Pro 10:04:42 example_test_directory  >  nosete            ",{}]]},"cursor":{"x":60}}],[0.06313299999999999,{"lines":{"12":[["Johns-MacBook-Pro 10:04:42 example_test_directory  >  nosetes           ",{}]]},"cursor":{"x":61}}],[0.064484,{"lines":{"12":[["Johns-MacBook-Pro 10:04:42 example_test_directory  >  nosetest          ",{}]]},"cursor":{"x":62}}],[0.128037,{"lines":{"12":[["Johns-MacBook-Pro 10:04:42 example_test_directory  >  nosetests         ",{}]]},"cursor":{"x":63}}],[0.319716,{"cursor":{"x":64}}],[0.119886,{"lines":{"12":[["Johns-MacBook-Pro 10:04:42 example_test_directory  >  nosetests -       ",{}]]},"cursor":{"x":65}}],[0.159965,{"lines":{"12":[["Johns-MacBook-Pro 10:04:42 example_test_directory  >  nosetests --      ",{}]]},"cursor":{"x":66}}],[0.328016,{"lines":{"12":[["Johns-MacBook-Pro 10:04:42 example_test_directory  >  nosetests --w     ",{}]]},"cursor":{"x":67}}],[0.064028,{"lines":{"12":[["Johns-MacBook-Pro 10:04:42 example_test_directory  >  nosetests --wi    ",{}]]},"cursor":{"x":68}}],[0.12791,{"lines":{"12":[["Johns-MacBook-Pro 10:04:42 example_test_directory  >  nosetests --wit   ",{}]]},"cursor":{"x":69}}],[0.056447,{"lines":{"12":[["Johns-MacBook-Pro 10:04:42 example_test_directory  >  nosetests --with  ",{}]]},"cursor":{"x":70}}],[0.207951,{"lines":{"12":[["Johns-MacBook-Pro 10:04:42 example_test_directory  >  nosetests --with- ",{}]]},"cursor":{"x":71}}],[0.151572,{"lines":{"12":[["Johns-MacBook-Pro 10:04:42 example_test_directory  >  nosetests --with-d",{}]]},"cursor":{"x":0,"y":13}}],[0.136429,{"lines":{"13":[["o                                                                       ",{}]]},"cursor":{"x":1}}],[0.112263,{"lines":{"13":[["oc                                                                      ",{}]]},"cursor":{"x":2}}],[0.151844,{"lines":{"13":[["oct                                                                     ",{}]]},"cursor":{"x":3}}],[0.151814,{"lines":{"13":[["octe                                                                    ",{}]]},"cursor":{"x":4}}],[0.047432,{"lines":{"13":[["octes                                                                   ",{}]]},"cursor":{"x":5}}],[0.06522799999999999,{"lines":{"13":[["octest                                                                  ",{}]]},"cursor":{"x":6}}],[0.287091,{"cursor":{"x":0,"y":14}}],[0.135092,{"lines":{"14":[[".                                                                       ",{}]]},"cursor":{"x":1}}],[0.015116,{"lines":{"14":[["..                                                                      ",{}]],"15":[["----------------------------------------------------------------------  ",{}]],"16":[["Ran 2 tests in 0.006s                                                   ",{}]],"18":[["OK                                                                      ",{}]],"19":[["Johns-MacBook-Pro 10:04:46 example_test_directory  >                    ",{}]]},"cursor":{"x":54,"y":19}}],[1.970431,{"lines":{"19":[["Johns-MacBook-Pro 10:04:46 example_test_directory  >  c                 ",{}]]},"cursor":{"x":55}}],[0.168007,{"lines":{"19":[["Johns-MacBook-Pro 10:04:46 example_test_directory  >  ca                ",{}]]},"cursor":{"x":56}}],[0.104461,{"lines":{"19":[["Johns-MacBook-Pro 10:04:46 example_test_directory  >  cat               ",{}]]},"cursor":{"x":57}}],[0.639115,{"cursor":{"x":58}}],[0.400146,{"lines":{"19":[["Johns-MacBook-Pro 10:04:46 example_test_directory  >  cat t             ",{}]]},"cursor":{"x":59}}],[0.416174,{"lines":{"19":[["Johns-MacBook-Pro 10:04:46 example_test_directory  >  cat toolz/        ",{}]]},"cursor":{"x":64}}],[0.56806,{}],[0.519836,{"cursor":{"x":0,"y":20}}],[6.500000000000001e-05,{"lines":{"0":[["Johns-MacBook-Pro 10:04:19 example_test_directory  >  ls                ",{}]],"1":[["Icon? ",{}],["toolz",{"fg":4}],["                                                             ",{}]],"2":[["Johns-MacBook-Pro 10:04:20 example_test_directory  >  # Regular tests on",{}]],"3":[["ly:                                                                     ",{}]],"4":[["Johns-MacBook-Pro 10:04:32 example_test_directory  >  nosetests         ",{}]],"5":[[".                                                                       ",{}]],"6":[["----------------------------------------------------------------------  ",{}]],"7":[["Ran 1 test in 0.002s                                                    ",{}]],"8":[["                                                                        ",{}]],"9":[["OK                                                                      ",{}]],"10":[["Johns-MacBook-Pro 10:04:36 example_test_directory  >  # With doctests:  ",{}]],"11":[["Johns-MacBook-Pro 10:04:42 example_test_directory  >  nosetests --with-d",{}]],"12":[["octest                                                                  ",{}]],"13":[["..                                                                      ",{}]],"14":[["----------------------------------------------------------------------  ",{}]],"15":[["Ran 2 tests in 0.006s                                                   ",{}]],"16":[["                                                                        ",{}]],"17":[["OK                                                                      ",{}]],"18":[["Johns-MacBook-Pro 10:04:46 example_test_directory  >  cat toolz/        ",{}]],"19":[["__init__.py    core.py        test_core.py                              ",{}]],"20":[["__init__.pyc   core.pyc       test_core.pyc                             ",{}]],"21":[["Johns-MacBook-Pro 10:04:46 example_test_directory  >  cat toolz/        ",{}]]},"cursor":{"x":64,"y":21}}],[1.527941,{"lines":{"21":[["Johns-MacBook-Pro 10:04:46 example_test_directory  >  cat toolz/c       ",{}]]},"cursor":{"x":65}}],[0.056042,{"lines":{"21":[["Johns-MacBook-Pro 10:04:46 example_test_directory  >  cat toolz/co      ",{}]]},"cursor":{"x":66}}],[0.119945,{"lines":{"21":[["Johns-MacBook-Pro 10:04:46 example_test_directory  >  cat toolz/cor     ",{}]]},"cursor":{"x":67}}],[0.087981,{"lines":{"21":[["Johns-MacBook-Pro 10:04:46 example_test_directory  >  cat toolz/core    ",{}]]},"cursor":{"x":68}}],[0.320025,{}],[2.2e-05,{"lines":{"21":[["Johns-MacBook-Pro 10:04:46 example_test_directory  >  cat toolz/core.py ",{}]]},"cursor":{"x":71}}],[0.368055,{"lines":{"0":[["Icon? ",{}],["toolz",{"fg":4}],["                                                             ",{}]],"1":[["Johns-MacBook-Pro 10:04:20 example_test_directory  >  # Regular tests on",{}]],"2":[["ly:                                                                     ",{}]],"3":[["Johns-MacBook-Pro 10:04:32 example_test_directory  >  nosetests         ",{}]],"4":[[".                                                                       ",{}]],"5":[["----------------------------------------------------------------------  ",{}]],"6":[["Ran 1 test in 0.002s                                                    ",{}]],"7":[["                                                                        ",{}]],"8":[["OK                                                                      ",{}]],"9":[["Johns-MacBook-Pro 10:04:36 example_test_directory  >  # With doctests:  ",{}]],"10":[["Johns-MacBook-Pro 10:04:42 example_test_directory  >  nosetests --with-d",{}]],"11":[["octest                                                                  ",{}]],"12":[["..                                                                      ",{}]],"13":[["----------------------------------------------------------------------  ",{}]],"14":[["Ran 2 tests in 0.006s                                                   ",{}]],"15":[["                                                                        ",{}]],"16":[["OK                                                                      ",{}]],"17":[["Johns-MacBook-Pro 10:04:46 example_test_directory  >  cat toolz/        ",{}]],"18":[["__init__.py    core.py        test_core.py                              ",{}]],"19":[["__init__.pyc   core.pyc       test_core.pyc                             ",{}]],"20":[["Johns-MacBook-Pro 10:04:46 example_test_directory  >  cat toolz/core.py ",{}]],"21":[["                                                                        ",{}]]},"cursor":{"x":0}}],[0.011404,{"lines":{"0":[["Ran 1 test in 0.002s                                                    ",{}]],"1":[["                                                                        ",{}]],"2":[["OK                                                                      ",{}]],"3":[["Johns-MacBook-Pro 10:04:36 example_test_directory  >  # With doctests:  ",{}]],"4":[["Johns-MacBook-Pro 10:04:42 example_test_directory  >  nosetests --with-d",{}]],"5":[["octest                                                                  ",{}]],"6":[["..                                                                      ",{}]],"7":[["----------------------------------------------------------------------  ",{}]],"8":[["Ran 2 tests in 0.006s                                                   ",{}]],"9":[["                                                                        ",{}]],"10":[["OK                                                                      ",{}]],"11":[["Johns-MacBook-Pro 10:04:46 example_test_directory  >  cat toolz/        ",{}]],"12":[["__init__.py    core.py        test_core.py                              ",{}]],"13":[["__init__.pyc   core.pyc       test_core.pyc                             ",{}]],"14":[["Johns-MacBook-Pro 10:04:46 example_test_directory  >  cat toolz/core.py ",{}]],"15":[["def a():                                                                ",{}]],"16":[["    \"\"\"                                                                 ",{}]],"17":[["    >>> 1                                                               ",{}]],"18":[["    1                                                                   ",{}]],"19":[["    \"\"\"                                                                 ",{}]],"20":[["    pass                                                                ",{}]],"21":[["Johns-MacBook-Pro 10:04:53 example_test_directory  >                    ",{}]]},"cursor":{"x":54}}],[4.652423,{"lines":{"21":[["Johns-MacBook-Pro 10:04:53 example_test_directory  >  c                 ",{}]]},"cursor":{"x":55}}],[0.144014,{"lines":{"21":[["Johns-MacBook-Pro 10:04:53 example_test_directory  >  ca                ",{}]]},"cursor":{"x":56}}],[0.103932,{"lines":{"21":[["Johns-MacBook-Pro 10:04:53 example_test_directory  >  cat               ",{}]]},"cursor":{"x":57}}],[0.168244,{"cursor":{"x":58}}],[1.271808,{"lines":{"21":[["Johns-MacBook-Pro 10:04:53 example_test_directory  >  cat t             ",{}]]},"cursor":{"x":59}}],[0.080208,{"lines":{"21":[["Johns-MacBook-Pro 10:04:53 example_test_directory  >  cat to            ",{}]]},"cursor":{"x":60}}],[0.249426,{"lines":{"21":[["Johns-MacBook-Pro 10:04:53 example_test_directory  >  cat toolz/        ",{}]]},"cursor":{"x":64}}],[0.606371,{"lines":{"21":[["Johns-MacBook-Pro 10:04:53 example_test_directory  >  cat toolz/t       ",{}]]},"cursor":{"x":65}}],[0.088007,{"lines":{"21":[["Johns-MacBook-Pro 10:04:53 example_test_directory  >  cat toolz/te      ",{}]]},"cursor":{"x":66}}],[0.087501,{"lines":{"21":[["Johns-MacBook-Pro 10:04:53 example_test_directory  >  cat toolz/tes     ",{}]]},"cursor":{"x":67}}],[0.055917,{"lines":{"21":[["Johns-MacBook-Pro 10:04:53 example_test_directory  >  cat toolz/test    ",{}]]},"cursor":{"x":68}}],[0.247954,{}],[2.6e-05,{"lines":{"0":[["                                                                        ",{}]],"1":[["OK                                                                      ",{}]],"2":[["Johns-MacBook-Pro 10:04:36 example_test_directory  >  # With doctests:  ",{}]],"3":[["Johns-MacBook-Pro 10:04:42 example_test_directory  >  nosetests --with-d",{}]],"4":[["octest                                                                  ",{}]],"5":[["..                                                                      ",{}]],"6":[["----------------------------------------------------------------------  ",{}]],"7":[["Ran 2 tests in 0.006s                                                   ",{}]],"8":[["                                                                        ",{}]],"9":[["OK                                                                      ",{}]],"10":[["Johns-MacBook-Pro 10:04:46 example_test_directory  >  cat toolz/        ",{}]],"11":[["__init__.py    core.py        test_core.py                              ",{}]],"12":[["__init__.pyc   core.pyc       test_core.pyc                             ",{}]],"13":[["Johns-MacBook-Pro 10:04:46 example_test_directory  >  cat toolz/core.py ",{}]],"14":[["def a():                                                                ",{}]],"15":[["    \"\"\"                                                                 ",{}]],"16":[["    >>> 1                                                               ",{}]],"17":[["    1                                                                   ",{}]],"18":[["    \"\"\"                                                                 ",{}]],"19":[["    pass                                                                ",{}]],"20":[["Johns-MacBook-Pro 10:04:53 example_test_directory  >  cat toolz/test_cor",{}]],"21":[["e.py                                                                    ",{}]]},"cursor":{"x":4}}],[0.76003,{"lines":{"0":[["OK                                                                      ",{}]],"1":[["Johns-MacBook-Pro 10:04:36 example_test_directory  >  # With doctests:  ",{}]],"2":[["Johns-MacBook-Pro 10:04:42 example_test_directory  >  nosetests --with-d",{}]],"3":[["octest                                                                  ",{}]],"4":[["..                                                                      ",{}]],"5":[["----------------------------------------------------------------------  ",{}]],"6":[["Ran 2 tests in 0.006s                                                   ",{}]],"7":[["                                                                        ",{}]],"8":[["OK                                                                      ",{}]],"9":[["Johns-MacBook-Pro 10:04:46 example_test_directory  >  cat toolz/        ",{}]],"10":[["__init__.py    core.py        test_core.py                              ",{}]],"11":[["__init__.pyc   core.pyc       test_core.pyc                             ",{}]],"12":[["Johns-MacBook-Pro 10:04:46 example_test_directory  >  cat toolz/core.py ",{}]],"13":[["def a():                                                                ",{}]],"14":[["    \"\"\"                                                                 ",{}]],"15":[["    >>> 1                                                               ",{}]],"16":[["    1                                                                   ",{}]],"17":[["    \"\"\"                                                                 ",{}]],"18":[["    pass                                                                ",{}]],"19":[["Johns-MacBook-Pro 10:04:53 example_test_directory  >  cat toolz/test_cor",{}]],"20":[["e.py                                                                    ",{}]],"21":[["                                                                        ",{}]]},"cursor":{"x":0}}],[0.012917,{"lines":{"0":[["Johns-MacBook-Pro 10:04:42 example_test_directory  >  nosetests --with-d",{}]],"1":[["octest                                                                  ",{}]],"2":[["..                                                                      ",{}]],"3":[["----------------------------------------------------------------------  ",{}]],"4":[["Ran 2 tests in 0.006s                                                   ",{}]],"5":[["                                                                        ",{}]],"6":[["OK                                                                      ",{}]],"7":[["Johns-MacBook-Pro 10:04:46 example_test_directory  >  cat toolz/        ",{}]],"8":[["__init__.py    core.py        test_core.py                              ",{}]],"9":[["__init__.pyc   core.pyc       test_core.pyc                             ",{}]],"10":[["Johns-MacBook-Pro 10:04:46 example_test_directory  >  cat toolz/core.py ",{}]],"11":[["def a():                                                                ",{}]],"12":[["    \"\"\"                                                                 ",{}]],"13":[["    >>> 1                                                               ",{}]],"14":[["    1                                                                   ",{}]],"15":[["    \"\"\"                                                                 ",{}]],"16":[["    pass                                                                ",{}]],"17":[["Johns-MacBook-Pro 10:04:53 example_test_directory  >  cat toolz/test_cor",{}]],"18":[["e.py                                                                    ",{}]],"19":[["def test_a():                                                           ",{}]],"20":[["    pass                                                                ",{}]],"21":[["Johns-MacBook-Pro 10:05:01 example_test_directory  >                    ",{}]]},"cursor":{"x":54}}],[3.259693,{"lines":{"21":[["Johns-MacBook-Pro 10:05:01 example_test_directory  >  v                 ",{}]]},"cursor":{"x":55}}],[0.08117000000000001,{"lines":{"21":[["Johns-MacBook-Pro 10:05:01 example_test_directory  >  vi                ",{}]]},"cursor":{"x":56}}],[0.102648,{"cursor":{"x":57}}],[0.319691,{"lines":{"21":[["Johns-MacBook-Pro 10:05:01 example_test_directory  >  vi t              ",{}]]},"cursor":{"x":58}}],[0.055994,{"lines":{"21":[["Johns-MacBook-Pro 10:05:01 example_test_directory  >  vi to             ",{}]]},"cursor":{"x":59}}],[0.256131,{"lines":{"21":[["Johns-MacBook-Pro 10:05:01 example_test_directory  >  vi toolz/         ",{}]]},"cursor":{"x":63}}],[0.8877620000000001,{"lines":{"21":[["Johns-MacBook-Pro 10:05:01 example_test_directory  >  vi toolz/c        ",{}]]},"cursor":{"x":64}}],[0.048061,{"lines":{"21":[["Johns-MacBook-Pro 10:05:01 example_test_directory  >  vi toolz/co       ",{}]]},"cursor":{"x":65}}],[0.200178,{"lines":{"21":[["Johns-MacBook-Pro 10:05:01 example_test_directory  >  vi toolz/core.py  ",{}]]},"cursor":{"x":70}}],[0.487734,{"lines":{"0":[["octest                                                                  ",{}]],"1":[["..                                                                      ",{}]],"2":[["----------------------------------------------------------------------  ",{}]],"3":[["Ran 2 tests in 0.006s                                                   ",{}]],"4":[["                                                                        ",{}]],"5":[["OK                                                                      ",{}]],"6":[["Johns-MacBook-Pro 10:04:46 example_test_directory  >  cat toolz/        ",{}]],"7":[["__init__.py    core.py        test_core.py                              ",{}]],"8":[["__init__.pyc   core.pyc       test_core.pyc                             ",{}]],"9":[["Johns-MacBook-Pro 10:04:46 example_test_directory  >  cat toolz/core.py ",{}]],"10":[["def a():                                                                ",{}]],"11":[["    \"\"\"                                                                 ",{}]],"12":[["    >>> 1                                                               ",{}]],"13":[["    1                                                                   ",{}]],"14":[["    \"\"\"                                                                 ",{}]],"15":[["    pass                                                                ",{}]],"16":[["Johns-MacBook-Pro 10:04:53 example_test_directory  >  cat toolz/test_cor",{}]],"17":[["e.py                                                                    ",{}]],"18":[["def test_a():                                                           ",{}]],"19":[["    pass                                                                ",{}]],"20":[["Johns-MacBook-Pro 10:05:01 example_test_directory  >  vi toolz/core.py  ",{}]],"21":[["                                                                        ",{}]]},"cursor":{"x":0}}],[0.053335,{"lines":{"0":[["                                                                        ",{}]],"1":[["                                                                        ",{}]],"2":[["                                                                        ",{}]],"3":[["                                                                        ",{}]],"5":[["                                                                        ",{}]],"6":[["                                                                        ",{}]],"7":[["                                                                        ",{}]],"8":[["                                                                        ",{}]],"9":[["                                                                        ",{}]],"10":[["                                                                        ",{}]],"11":[["                                                                        ",{}]],"12":[["                                                                        ",{}]],"13":[["                                                                        ",{}]],"14":[["                                                                        ",{}]],"15":[["                                                                        ",{}]],"16":[["                                                                        ",{}]],"17":[["                                                                        ",{}]],"18":[["                                                                        ",{}]],"19":[["                                                                        ",{}]],"20":[["                                                                        ",{}]]}}],[0.00377,{"lines":{"0":[["def a():                                                                ",{}]],"1":[["    \"\"\"                                                                 ",{}]],"2":[["    >>> 1                                                               ",{}]],"3":[["    1                                                                   ",{}]],"4":[["    \"\"\"                                                                 ",{}]],"5":[["    pass                                                                ",{}]],"6":[["~                                                                       ",{"fg":12}]],"7":[["~                                                                       ",{"fg":12}]],"8":[["~                                                                       ",{"fg":12}]],"9":[["~                                                                       ",{"fg":12}]],"10":[["~                                                                       ",{"fg":12}]],"11":[["~                                                                       ",{"fg":12}]],"12":[["~                                                                       ",{"fg":12}]],"13":[["~                                                                       ",{"fg":12}]],"14":[["~                                                                       ",{"fg":12}]],"15":[["~                                                                       ",{"fg":12}]],"16":[["~                                                                       ",{"fg":12}]],"17":[["~                                                                       ",{"fg":12}]],"18":[["~                                                                       ",{"fg":12}]],"19":[["~                                                                       ",{"fg":12}]],"20":[["~                                                                       ",{"fg":12}]],"21":[["\"toolz/core.py\" 6L, 50C                                                 ",{}]]},"cursor":{"y":0}}],[1.280143,{}],[0.392162,{"cursor":{"y":1}}],[0.183841,{"cursor":{"y":2}}],[0.168155,{"cursor":{"y":3}}],[0.408404,{"cursor":{"y":2}}],[0.750611,{"cursor":{"x":8}}],[1.144594,{"lines":{"2":[["    >>>                                                                 ",{}]]},"cursor":{"x":7}}],[0.48758,{"lines":{"21":[["-- INSERT --",{"bold":true}],["                                                            ",{}]]},"cursor":{"x":12,"y":21,"visible":false}}],[0.000132,{"cursor":{"x":8,"y":2,"visible":true}}],[0.39199,{"lines":{"2":[["    >>> 0                                                               ",{}]]},"cursor":{"x":9}}],[1.033873,{"lines":{"21":[["                                                                        ",{}]]},"cursor":{"x":8}}],[0.8941789999999999,{"cursor":{"visible":false}}],[0.000177,{"cursor":{"visible":true}}],[0.167254,{"lines":{"21":[["\"toolz/core.py\"                                                         ",{}]]},"cursor":{"x":15,"y":21,"visible":false}}],[0.005181,{"lines":{"0":[["octest                                                                  ",{}]],"1":[["..                                                                      ",{}]],"2":[["----------------------------------------------------------------------  ",{}]],"3":[["Ran 2 tests in 0.006s                                                   ",{}]],"4":[["                                                                        ",{}]],"5":[["OK                                                                      ",{}]],"6":[["Johns-MacBook-Pro 10:04:46 example_test_directory  >  cat toolz/        ",{}]],"7":[["__init__.py    core.py        test_core.py                              ",{}]],"8":[["__init__.pyc   core.pyc       test_core.pyc                             ",{}]],"9":[["Johns-MacBook-Pro 10:04:46 example_test_directory  >  cat toolz/core.py ",{}]],"10":[["def a():                                                                ",{}]],"11":[["    \"\"\"                                                                 ",{}]],"12":[["    >>> 1                                                               ",{}]],"13":[["    1                                                                   ",{}]],"14":[["    \"\"\"                                                                 ",{}]],"15":[["    pass                                                                ",{}]],"16":[["Johns-MacBook-Pro 10:04:53 example_test_directory  >  cat toolz/test_cor",{}]],"17":[["e.py                                                                    ",{}]],"18":[["def test_a():                                                           ",{}]],"19":[["    pass                                                                ",{}]],"20":[["Johns-MacBook-Pro 10:05:01 example_test_directory  >  vi toolz/core.py  ",{}]],"21":[["                                                                        ",{}]]},"cursor":{"x":0,"visible":true}}],[0.014939,{"lines":{"21":[["Johns-MacBook-Pro 10:05:14 example_test_directory  >                    ",{}]]},"cursor":{"x":54}}],[2.956012,{"lines":{"21":[["Johns-MacBook-Pro 10:05:14 example_test_directory  >  n                 ",{}]]},"cursor":{"x":55}}],[0.071895,{"lines":{"21":[["Johns-MacBook-Pro 10:05:14 example_test_directory  >  no                ",{}]]},"cursor":{"x":56}}],[0.074169,{"lines":{"21":[["Johns-MacBook-Pro 10:05:14 example_test_directory  >  nos               ",{}]]},"cursor":{"x":57}}],[0.06962400000000001,{"lines":{"21":[["Johns-MacBook-Pro 10:05:14 example_test_directory  >  nose              ",{}]]},"cursor":{"x":58}}],[0.576363,{"lines":{"21":[["Johns-MacBook-Pro 10:05:14 example_test_directory  >  noset             ",{}]]},"cursor":{"x":59}}],[0.06498,{"lines":{"21":[["Johns-MacBook-Pro 10:05:14 example_test_directory  >  nosete            ",{}]]},"cursor":{"x":60}}],[0.086921,{"lines":{"21":[["Johns-MacBook-Pro 10:05:14 example_test_directory  >  nosetes           ",{}]]},"cursor":{"x":61}}],[0.039602,{"lines":{"21":[["Johns-MacBook-Pro 10:05:14 example_test_directory  >  nosetest          ",{}]]},"cursor":{"x":62}}],[0.127956,{"lines":{"21":[["Johns-MacBook-Pro 10:05:14 example_test_directory  >  nosetests         ",{}]]},"cursor":{"x":63}}],[0.592264,{"lines":{"0":[["..                                                                      ",{}]],"1":[["----------------------------------------------------------------------  ",{}]],"2":[["Ran 2 tests in 0.006s                                                   ",{}]],"3":[["                                                                        ",{}]],"4":[["OK                                                                      ",{}]],"5":[["Johns-MacBook-Pro 10:04:46 example_test_directory  >  cat toolz/        ",{}]],"6":[["__init__.py    core.py        test_core.py                              ",{}]],"7":[["__init__.pyc   core.pyc       test_core.pyc                             ",{}]],"8":[["Johns-MacBook-Pro 10:04:46 example_test_directory  >  cat toolz/core.py ",{}]],"9":[["def a():                                                                ",{}]],"10":[["    \"\"\"                                                                 ",{}]],"11":[["    >>> 1                                                               ",{}]],"12":[["    1                                                                   ",{}]],"13":[["    \"\"\"                                                                 ",{}]],"14":[["    pass                                                                ",{}]],"15":[["Johns-MacBook-Pro 10:04:53 example_test_directory  >  cat toolz/test_cor",{}]],"16":[["e.py                                                                    ",{}]],"17":[["def test_a():                                                           ",{}]],"18":[["    pass                                                                ",{}]],"19":[["Johns-MacBook-Pro 10:05:01 example_test_directory  >  vi toolz/core.py  ",{}]],"20":[["Johns-MacBook-Pro 10:05:14 example_test_directory  >  nosetests         ",{}]],"21":[["                                                                        ",{}]]},"cursor":{"x":0}}],[0.138747,{"lines":{"21":[[".                                                                       ",{}]]},"cursor":{"x":1}}],[0.015565,{"lines":{"0":[["Johns-MacBook-Pro 10:04:46 example_test_directory  >  cat toolz/        ",{}]],"1":[["__init__.py    core.py        test_core.py                              ",{}]],"2":[["__init__.pyc   core.pyc       test_core.pyc                             ",{}]],"3":[["Johns-MacBook-Pro 10:04:46 example_test_directory  >  cat toolz/core.py ",{}]],"4":[["def a():                                                                ",{}]],"5":[["    \"\"\"                                                                 ",{}]],"6":[["    >>> 1                                                               ",{}]],"7":[["    1                                                                   ",{}]],"8":[["    \"\"\"                                                                 ",{}]],"9":[["    pass                                                                ",{}]],"10":[["Johns-MacBook-Pro 10:04:53 example_test_directory  >  cat toolz/test_cor",{}]],"11":[["e.py                                                                    ",{}]],"12":[["def test_a():                                                           ",{}]],"13":[["    pass                                                                ",{}]],"14":[["Johns-MacBook-Pro 10:05:01 example_test_directory  >  vi toolz/core.py  ",{}]],"15":[["Johns-MacBook-Pro 10:05:14 example_test_directory  >  nosetests         ",{}]],"16":[[".                                                                       ",{}]],"17":[["----------------------------------------------------------------------  ",{}]],"18":[["Ran 1 test in 0.002s                                                    ",{}]],"19":[["                                                                        ",{}]],"20":[["OK                                                                      ",{}]],"21":[["Johns-MacBook-Pro 10:05:19 example_test_directory  >                    ",{}]]},"cursor":{"x":54}}],[0.831336,{"lines":{"21":[["Johns-MacBook-Pro 10:05:19 example_test_directory  >  nosetests         ",{}]]},"cursor":{"x":63}}],[0.224152,{"lines":{"21":[["Johns-MacBook-Pro 10:05:19 example_test_directory  >  vi toolz/core.py  ",{}]]},"cursor":{"x":70}}],[0.399787,{"lines":{"0":[["__init__.py    core.py        test_core.py                              ",{}]],"1":[["__init__.pyc   core.pyc       test_core.pyc                             ",{}]],"2":[["Johns-MacBook-Pro 10:04:46 example_test_directory  >  cat toolz/core.py ",{}]],"3":[["def a():                                                                ",{}]],"4":[["    \"\"\"                                                                 ",{}]],"5":[["    >>> 1                                                               ",{}]],"6":[["    1                                                                   ",{}]],"7":[["    \"\"\"                                                                 ",{}]],"8":[["    pass                                                                ",{}]],"9":[["Johns-MacBook-Pro 10:04:53 example_test_directory  >  cat toolz/test_cor",{}]],"10":[["e.py                                                                    ",{}]],"11":[["def test_a():                                                           ",{}]],"12":[["    pass                                                                ",{}]],"13":[["Johns-MacBook-Pro 10:05:01 example_test_directory  >  vi toolz/core.py  ",{}]],"14":[["Johns-MacBook-Pro 10:05:14 example_test_directory  >  nosetests         ",{}]],"15":[[".                                                                       ",{}]],"16":[["----------------------------------------------------------------------  ",{}]],"17":[["Ran 1 test in 0.002s                                                    ",{}]],"18":[["                                                                        ",{}]],"19":[["OK                                                                      ",{}]],"20":[["Johns-MacBook-Pro 10:05:19 example_test_directory  >  cat toolz/test_cor",{}]],"21":[["e.py                                                                    ",{}]]},"cursor":{"x":4}}],[0.5595599999999999,{"lines":{"20":[["Johns-MacBook-Pro 10:05:19 example_test_directory  >  cat toolz/core.py ",{}]]},"cursor":{"x":0}}],[1.9e-05,{"lines":{"21":[["                                                                        ",{}]]},"cursor":{"x":71,"y":20}}],[0.423993,{"lines":{"20":[["Johns-MacBook-Pro 10:05:19 example_test_directory  >  nosetests --with-d",{}]],"21":[["octest                                                                  ",{}]]},"cursor":{"x":6,"y":21}}],[1.574835,{"lines":{"0":[["__init__.pyc   core.pyc       test_core.pyc                             ",{}]],"1":[["Johns-MacBook-Pro 10:04:46 example_test_directory  >  cat toolz/core.py ",{}]],"2":[["def a():                                                                ",{}]],"3":[["    \"\"\"                                                                 ",{}]],"4":[["    >>> 1                                                               ",{}]],"5":[["    1                                                                   ",{}]],"6":[["    \"\"\"                                                                 ",{}]],"7":[["    pass                                                                ",{}]],"8":[["Johns-MacBook-Pro 10:04:53 example_test_directory  >  cat toolz/test_cor",{}]],"9":[["e.py                                                                    ",{}]],"10":[["def test_a():                                                           ",{}]],"11":[["    pass                                                                ",{}]],"12":[["Johns-MacBook-Pro 10:05:01 example_test_directory  >  vi toolz/core.py  ",{}]],"13":[["Johns-MacBook-Pro 10:05:14 example_test_directory  >  nosetests         ",{}]],"14":[[".                                                                       ",{}]],"15":[["----------------------------------------------------------------------  ",{}]],"16":[["Ran 1 test in 0.002s                                                    ",{}]],"17":[["                                                                        ",{}]],"18":[["OK                                                                      ",{}]],"19":[["Johns-MacBook-Pro 10:05:19 example_test_directory  >  nosetests --with-d",{}]],"20":[["octest                                                                  ",{}]],"21":[["                                                                        ",{}]]},"cursor":{"x":0}}],[0.140813,{"lines":{"21":[["F                                                                       ",{}]]},"cursor":{"x":1}}],[0.0006309999999999999,{"lines":{"0":[[" 2163, in runTest                                                       ",{}]],"1":[["    raise self.failureException(self.format_failure(new.getvalue()))    ",{}]],"2":[["AssertionError: Failed doctest test for toolz.core.a                    ",{}]],"3":[["  File \"/Users/jacobsen/Dropbox/example_test_directory/toolz/core.py\", l",{}]],"4":[["ine 1, in a                                                             ",{}]],"5":[["                                                                        ",{}]],"6":[["----------------------------------------------------------------------  ",{}]],"7":[["File \"/Users/jacobsen/Dropbox/example_test_directory/toolz/core.py\", lin",{}]],"8":[["e 3, in toolz.core.a                                                    ",{}]],"9":[["Failed example:                                                         ",{}]],"10":[["    0                                                                   ",{}]],"11":[["Expected:                                                               ",{}]],"12":[["    1                                                                   ",{}]],"13":[["Got:                                                                    ",{}]],"14":[["    0                                                                   ",{}]],"15":[["                                                                        ",{}]],"16":[["                                                                        ",{}]],"17":[["----------------------------------------------------------------------  ",{}]],"18":[["Ran 2 tests in 0.007s                                                   ",{}]],"19":[["                                                                        ",{}]],"20":[["FAILED (failures=1)                                                     ",{}]],"21":[["                                                                        ",{}]]},"cursor":{"x":0}}],[0.018259,{"lines":{"21":[["Johns-MacBook-Pro 10:05:23 example_test_directory  >                    ",{}]]},"cursor":{"x":54}}],[3.456456,{"lines":{"21":[["Johns-MacBook-Pro 10:05:23 example_test_directory  >  !                 ",{}]]},"cursor":{"x":55}}],[0.288195,{"lines":{"21":[["Johns-MacBook-Pro 10:05:23 example_test_directory  >  !v                ",{}]]},"cursor":{"x":56}}],[0.03934,{"lines":{"21":[["Johns-MacBook-Pro 10:05:23 example_test_directory  >  !vi               ",{}]]},"cursor":{"x":57}}],[0.392606,{"lines":{"0":[["    raise self.failureException(self.format_failure(new.getvalue()))    ",{}]],"1":[["AssertionError: Failed doctest test for toolz.core.a                    ",{}]],"2":[["  File \"/Users/jacobsen/Dropbox/example_test_directory/toolz/core.py\", l",{}]],"3":[["ine 1, in a                                                             ",{}]],"4":[["                                                                        ",{}]],"5":[["----------------------------------------------------------------------  ",{}]],"6":[["File \"/Users/jacobsen/Dropbox/example_test_directory/toolz/core.py\", lin",{}]],"7":[["e 3, in toolz.core.a                                                    ",{}]],"8":[["Failed example:                                                         ",{}]],"9":[["    0                                                                   ",{}]],"10":[["Expected:                                                               ",{}]],"11":[["    1                                                                   ",{}]],"12":[["Got:                                                                    ",{}]],"13":[["    0                                                                   ",{}]],"14":[["                                                                        ",{}]],"16":[["----------------------------------------------------------------------  ",{}]],"17":[["Ran 2 tests in 0.007s                                                   ",{}]],"18":[["                                                                        ",{}]],"19":[["FAILED (failures=1)                                                     ",{}]],"20":[["Johns-MacBook-Pro 10:05:23 example_test_directory  >  !vi               ",{}]],"21":[["                                                                        ",{}]]},"cursor":{"x":0}}],[0.011479,{"lines":{"0":[["def a():                                                                ",{}]],"1":[["    \"\"\"                                                                 ",{}]],"2":[["    >>> 0                                                               ",{}]],"3":[["    1                                                                   ",{}]],"4":[["    \"\"\"                                                                 ",{}]],"5":[["    pass                                                                ",{}]],"6":[["~                                                                       ",{"fg":12}]],"7":[["~                                                                       ",{"fg":12}]],"8":[["~                                                                       ",{"fg":12}]],"9":[["~                                                                       ",{"fg":12}]],"10":[["~                                                                       ",{"fg":12}]],"11":[["~                                                                       ",{"fg":12}]],"12":[["~                                                                       ",{"fg":12}]],"13":[["~                                                                       ",{"fg":12}]],"14":[["~                                                                       ",{"fg":12}]],"15":[["~                                                                       ",{"fg":12}]],"16":[["~                                                                       ",{"fg":12}]],"17":[["~                                                                       ",{"fg":12}]],"18":[["~                                                                       ",{"fg":12}]],"19":[["~                                                                       ",{"fg":12}]],"20":[["~                                                                       ",{"fg":12}]],"21":[["\"toolz/core.py\" 6L, 50C                                                 ",{}]]},"cursor":{"y":0}}],[0.789895,{"cursor":{"y":1}}],[0.184005,{"cursor":{"y":2}}],[0.151337,{"cursor":{"y":3}}],[0.328704,{"cursor":{"x":1}}],[0.231813,{"cursor":{"x":2}}],[0.16755,{"cursor":{"x":3}}],[0.152338,{"cursor":{"x":4}}],[0.342841,{"lines":{"3":[["    0                                                                   ",{}]]}}],[0.647995,{"lines":{"21":[["\"toolz/core.py\"                                                         ",{}]]},"cursor":{"x":16,"y":21,"visible":false}}],[0.014394,{"lines":{"0":[["AssertionError: Failed doctest test for toolz.core.a                    ",{}]],"1":[["  File \"/Users/jacobsen/Dropbox/example_test_directory/toolz/core.py\", l",{}]],"2":[["ine 1, in a                                                             ",{}]],"3":[["                                                                        ",{}]],"4":[["----------------------------------------------------------------------  ",{}]],"5":[["File \"/Users/jacobsen/Dropbox/example_test_directory/toolz/core.py\", lin",{}]],"6":[["e 3, in toolz.core.a                                                    ",{}]],"7":[["Failed example:                                                         ",{}]],"8":[["    0                                                                   ",{}]],"9":[["Expected:                                                               ",{}]],"10":[["    1                                                                   ",{}]],"11":[["Got:                                                                    ",{}]],"12":[["    0                                                                   ",{}]],"13":[["                                                                        ",{}]],"14":[["                                                                        ",{}]],"15":[["----------------------------------------------------------------------  ",{}]],"16":[["Ran 2 tests in 0.007s                                                   ",{}]],"17":[["                                                                        ",{}]],"18":[["FAILED (failures=1)                                                     ",{}]],"19":[["Johns-MacBook-Pro 10:05:23 example_test_directory  >  !vi               ",{}]],"20":[["vi toolz/core.py                                                        ",{}]],"21":[["Johns-MacBook-Pro 10:05:31 example_test_directory  >                    ",{}]]},"cursor":{"x":54,"visible":true}}],[1.536974,{"lines":{"21":[["Johns-MacBook-Pro 10:05:31 example_test_directory  >  !                 ",{}]]},"cursor":{"x":55}}],[0.248499,{"lines":{"21":[["Johns-MacBook-Pro 10:05:31 example_test_directory  >  !n                ",{}]]},"cursor":{"x":56}}],[0.047385,{"lines":{"21":[["Johns-MacBook-Pro 10:05:31 example_test_directory  >  !no               ",{}]]},"cursor":{"x":57}}],[0.649637,{"lines":{"0":[["  File \"/Users/jacobsen/Dropbox/example_test_directory/toolz/core.py\", l",{}]],"1":[["ine 1, in a                                                             ",{}]],"2":[["                                                                        ",{}]],"3":[["----------------------------------------------------------------------  ",{}]],"4":[["File \"/Users/jacobsen/Dropbox/example_test_directory/toolz/core.py\", lin",{}]],"5":[["e 3, in toolz.core.a                                                    ",{}]],"6":[["Failed example:                                                         ",{}]],"7":[["    0                                                                   ",{}]],"8":[["Expected:                                                               ",{}]],"9":[["    1                                                                   ",{}]],"10":[["Got:                                                                    ",{}]],"11":[["    0                                                                   ",{}]],"12":[["                                                                        ",{}]],"14":[["----------------------------------------------------------------------  ",{}]],"15":[["Ran 2 tests in 0.007s                                                   ",{}]],"16":[["                                                                        ",{}]],"17":[["FAILED (failures=1)                                                     ",{}]],"18":[["Johns-MacBook-Pro 10:05:23 example_test_directory  >  !vi               ",{}]],"19":[["vi toolz/core.py                                                        ",{}]],"20":[["Johns-MacBook-Pro 10:05:31 example_test_directory  >  !no               ",{}]],"21":[["                                                                        ",{}]]},"cursor":{"x":0}}],[0.000728,{"lines":{"0":[["ine 1, in a                                                             ",{}]],"1":[["                                                                        ",{}]],"2":[["----------------------------------------------------------------------  ",{}]],"3":[["File \"/Users/jacobsen/Dropbox/example_test_directory/toolz/core.py\", lin",{}]],"4":[["e 3, in toolz.core.a                                                    ",{}]],"5":[["Failed example:                                                         ",{}]],"6":[["    0                                                                   ",{}]],"7":[["Expected:                                                               ",{}]],"8":[["    1                                                                   ",{}]],"9":[["Got:                                                                    ",{}]],"10":[["    0                                                                   ",{}]],"11":[["                                                                        ",{}]],"13":[["----------------------------------------------------------------------  ",{}]],"14":[["Ran 2 tests in 0.007s                                                   ",{}]],"15":[["                                                                        ",{}]],"16":[["FAILED (failures=1)                                                     ",{}]],"17":[["Johns-MacBook-Pro 10:05:23 example_test_directory  >  !vi               ",{}]],"18":[["vi toolz/core.py                                                        ",{}]],"19":[["Johns-MacBook-Pro 10:05:31 example_test_directory  >  !no               ",{}]],"20":[["nosetests --with-doctest                                                ",{}]]}}],[0.138423,{"lines":{"21":[[".                                                                       ",{}]]},"cursor":{"x":1}}],[0.015653,{"lines":{"0":[["Failed example:                                                         ",{}]],"1":[["    0                                                                   ",{}]],"2":[["Expected:                                                               ",{}]],"3":[["    1                                                                   ",{}]],"4":[["Got:                                                                    ",{}]],"5":[["    0                                                                   ",{}]],"6":[["                                                                        ",{}]],"7":[["                                                                        ",{}]],"8":[["----------------------------------------------------------------------  ",{}]],"9":[["Ran 2 tests in 0.007s                                                   ",{}]],"10":[["                                                                        ",{}]],"11":[["FAILED (failures=1)                                                     ",{}]],"12":[["Johns-MacBook-Pro 10:05:23 example_test_directory  >  !vi               ",{}]],"13":[["vi toolz/core.py                                                        ",{}]],"14":[["Johns-MacBook-Pro 10:05:31 example_test_directory  >  !no               ",{}]],"15":[["nosetests --with-doctest                                                ",{}]],"16":[["..                                                                      ",{}]],"17":[["----------------------------------------------------------------------  ",{}]],"18":[["Ran 2 tests in 0.006s                                                   ",{}]],"19":[["                                                                        ",{}]],"20":[["OK                                                                      ",{}]],"21":[["Johns-MacBook-Pro 10:05:33 example_test_directory  >                    ",{}]]},"cursor":{"x":54}}],[4.963913,{"lines":{"0":[["    0                                                                   ",{}]],"1":[["Expected:                                                               ",{}]],"2":[["    1                                                                   ",{}]],"3":[["Got:                                                                    ",{}]],"4":[["    0                                                                   ",{}]],"5":[["                                                                        ",{}]],"7":[["----------------------------------------------------------------------  ",{}]],"8":[["Ran 2 tests in 0.007s                                                   ",{}]],"9":[["                                                                        ",{}]],"10":[["FAILED (failures=1)                                                     ",{}]],"11":[["Johns-MacBook-Pro 10:05:23 example_test_directory  >  !vi               ",{}]],"12":[["vi toolz/core.py                                                        ",{}]],"13":[["Johns-MacBook-Pro 10:05:31 example_test_directory  >  !no               ",{}]],"14":[["nosetests --with-doctest                                                ",{}]],"15":[["..                                                                      ",{}]],"16":[["----------------------------------------------------------------------  ",{}]],"17":[["Ran 2 tests in 0.006s                                                   ",{}]],"18":[["                                                                        ",{}]],"19":[["OK                                                                      ",{}]],"20":[["Johns-MacBook-Pro 10:05:33 example_test_directory  >  exit              ",{}]],"21":[["                                                                        ",{}]]},"cursor":{"x":0}}]]