[[0.121211,{"lines":{"0":[["                                                                                                                                      ",{}]],"1":[["                                                                                                                                      ",{}]],"2":[["                                                                                                                                      ",{}]],"3":[["                                                                                                                                      ",{}]],"4":[["                                                                                                                                      ",{}]],"5":[["                                                                                                                                      ",{}]],"6":[["                                                                                                                                      ",{}]],"7":[["                                                                                                                                      ",{}]],"8":[["                                                                                                                                      ",{}]],"9":[["                                                                                                                                      ",{}]],"10":[["                                                                                                                                      ",{}]],"11":[["                                                                                                                                      ",{}]],"12":[["                                                                                                                                      ",{}]],"13":[["                                                                                                                                      ",{}]],"14":[["                                                                                                                                      ",{}]],"15":[["                                                                                                                                      ",{}]],"16":[["                                                                                                                                      ",{}]],"17":[["                                                                                                                                      ",{}]],"18":[["                                                                                                                                      ",{}]],"19":[["                                                                                                                                      ",{}]],"20":[["                                                                                                                                      ",{}]],"21":[["                                                                                                                                      ",{}]],"22":[["                                                                                                                                      ",{}]],"23":[["                                                                                                                                      ",{}]],"24":[["                                                                                                                                      ",{}]],"25":[["                                                                                                                                      ",{}]],"26":[["                                                                                                                                      ",{}]],"27":[["                                                                                                                                      ",{}]],"28":[["                                                                                                                                      ",{}]],"29":[["                                                                                                                                      ",{}]]},"cursor":{"x":0,"y":0,"visible":true}}],[0.008779,{"lines":{"0":[["finn",{"fg":2}],["_",{"fg":7}],["air",{"fg":1}],[":",{"fg":7}],["~",{"fg":3}],["$ ",{"fg":7}],["                                                                                                                 ",{}],["[master]",{"fg":3}],[" ",{}]]},"cursor":{"x":12}}],[0.723909,{"lines":{"0":[["finn",{"fg":2}],["_",{"fg":7}],["air",{"fg":1}],[":",{"fg":7}],["~",{"fg":3}],["$ ",{"fg":7}],["c                                                                                                                ",{}],["[master]",{"fg":3}],[" ",{}]]},"cursor":{"x":13}}],[0.182317,{"lines":{"0":[["finn",{"fg":2}],["_",{"fg":7}],["air",{"fg":1}],[":",{"fg":7}],["~",{"fg":3}],["$ ",{"fg":7}],["co                                                                                                               ",{}],["[master]",{"fg":3}],[" ",{}]]},"cursor":{"x":14}}],[0.20794,{"lines":{"0":[["finn",{"fg":2}],["_",{"fg":7}],["air",{"fg":1}],[":",{"fg":7}],["~",{"fg":3}],["$ ",{"fg":7}],["cow                                                                                                              ",{}],["[master]",{"fg":3}],[" ",{}]]},"cursor":{"x":15}}],[0.526849,{"lines":{"0":[["finn",{"fg":2}],["_",{"fg":7}],["air",{"fg":1}],[":",{"fg":7}],["~",{"fg":3}],["$ ",{"fg":7}],["cows                                                                                                             ",{}],["[master]",{"fg":3}],[" ",{}]]},"cursor":{"x":16}}],[0.064651,{"lines":{"0":[["finn",{"fg":2}],["_",{"fg":7}],["air",{"fg":1}],[":",{"fg":7}],["~",{"fg":3}],["$ ",{"fg":7}],["cowsa                                                                                                            ",{}],["[master]",{"fg":3}],[" ",{}]]},"cursor":{"x":17}}],[0.816186,{"lines":{"0":[["finn",{"fg":2}],["_",{"fg":7}],["air",{"fg":1}],[":",{"fg":7}],["~",{"fg":3}],["$ ",{"fg":7}],["cowsay                                                                                                           ",{}],["[master]",{"fg":3}],[" ",{}]]},"cursor":{"x":18}}],[0.168294,{"cursor":{"x":19}}],[0.752126,{"lines":{"0":[["finn",{"fg":2}],["_",{"fg":7}],["air",{"fg":1}],[":",{"fg":7}],["~",{"fg":3}],["$ ",{"fg":7}],["cowsay H                                                                                                         ",{}],["[master]",{"fg":3}],[" ",{}]]},"cursor":{"x":20}}],[0.159805,{"lines":{"0":[["finn",{"fg":2}],["_",{"fg":7}],["air",{"fg":1}],[":",{"fg":7}],["~",{"fg":3}],["$ ",{"fg":7}],["cowsay Ha                                                                                                        ",{}],["[master]",{"fg":3}],[" ",{}]]},"cursor":{"x":21}}],[0.159588,{"lines":{"0":[["finn",{"fg":2}],["_",{"fg":7}],["air",{"fg":1}],[":",{"fg":7}],["~",{"fg":3}],["$ ",{"fg":7}],["cowsay Hal                                                                                                       ",{}],["[master]",{"fg":3}],[" ",{}]]},"cursor":{"x":22}}],[0.144494,{"lines":{"0":[["finn",{"fg":2}],["_",{"fg":7}],["air",{"fg":1}],[":",{"fg":7}],["~",{"fg":3}],["$ ",{"fg":7}],["cowsay Hall                                                                                                      ",{}],["[master]",{"fg":3}],[" ",{}]]},"cursor":{"x":23}}],[0.152093,{"lines":{"0":[["finn",{"fg":2}],["_",{"fg":7}],["air",{"fg":1}],[":",{"fg":7}],["~",{"fg":3}],["$ ",{"fg":7}],["cowsay Hallo                                                                                                     ",{}],["[master]",{"fg":3}],[" ",{}]]},"cursor":{"x":24}}],[0.111826,{"cursor":{"x":25}}],[0.143965,{"lines":{"0":[["finn",{"fg":2}],["_",{"fg":7}],["air",{"fg":1}],[":",{"fg":7}],["~",{"fg":3}],["$ ",{"fg":7}],["cowsay Hallo S                                                                                                   ",{}],["[master]",{"fg":3}],[" ",{}]]},"cursor":{"x":26}}],[0.192225,{"lines":{"0":[["finn",{"fg":2}],["_",{"fg":7}],["air",{"fg":1}],[":",{"fg":7}],["~",{"fg":3}],["$ ",{"fg":7}],["cowsay Hallo Sc                                                                                                  ",{}],["[master]",{"fg":3}],[" ",{}]]},"cursor":{"x":27}}],[0.112681,{"lines":{"0":[["finn",{"fg":2}],["_",{"fg":7}],["air",{"fg":1}],[":",{"fg":7}],["~",{"fg":3}],["$ ",{"fg":7}],["cowsay Hallo Sch                                                                                                 ",{}],["[master]",{"fg":3}],[" ",{}]]},"cursor":{"x":28}}],[0.175377,{"lines":{"0":[["finn",{"fg":2}],["_",{"fg":7}],["air",{"fg":1}],[":",{"fg":7}],["~",{"fg":3}],["$ ",{"fg":7}],["cowsay Hallo Schn                                                                                                ",{}],["[master]",{"fg":3}],[" ",{}]]},"cursor":{"x":29}}],[0.047385,{"lines":{"0":[["finn",{"fg":2}],["_",{"fg":7}],["air",{"fg":1}],[":",{"fg":7}],["~",{"fg":3}],["$ ",{"fg":7}],["cowsay Hallo Schnu                                                                                               ",{}],["[master]",{"fg":3}],[" ",{}]]},"cursor":{"x":30}}],[0.937063,{"lines":{"0":[["finn",{"fg":2}],["_",{"fg":7}],["air",{"fg":1}],[":",{"fg":7}],["~",{"fg":3}],["$ ",{"fg":7}],["cowsay Hallo Schnu!                                                                                              ",{}],["[master]",{"fg":3}],[" ",{}]]},"cursor":{"x":31}}],[1.055599,{}],[0.002288,{"cursor":{"x":0,"y":1}}],[0.029435,{"lines":{"1":[[" ______________                                                                                                                       ",{}]],"2":[["< Hallo Schnu! >                                                                                                                      ",{}]],"3":[[" --------------                                                                                                                       ",{}]],"4":[["        \\   ^__^                                                                                                                      ",{}]],"5":[["         \\  (oo)\\_______                                                                                                              ",{}]],"6":[["            (__)\\       )\\/\\                                                                                                          ",{}]],"7":[["                ||----w |                                                                                                             ",{}]],"8":[["                ||     ||                                                                                                             ",{}]]},"cursor":{"y":9}}],[0.008336999999999999,{"lines":{"9":[["finn",{"fg":2}],["_",{"fg":7}],["air",{"fg":1}],[":",{"fg":7}],["~",{"fg":3}],["$ ",{"fg":7}],["                                                                                                                 ",{}],["[master]",{"fg":3}],[" ",{}]]},"cursor":{"x":12}}],[2.617073,{"lines":{"9":[["finn",{"fg":2}],["_",{"fg":7}],["air",{"fg":1}],[":",{"fg":7}],["~",{"fg":3}],["$ ",{"fg":7}],["cowsay Hallo Schnu!                                                                                              ",{}],["[master]",{"fg":3}],[" ",{}]]},"cursor":{"x":31}}],[0.294358,{"lines":{"9":[["finn",{"fg":2}],["_",{"fg":7}],["air",{"fg":1}],[":",{"fg":7}],["~",{"fg":3}],["$ ",{"fg":7}],["cowsay Hallo Schnu                                                                                               ",{}],["[master]",{"fg":3}],[" ",{}]]},"cursor":{"x":30}}],[0.500736,{"lines":{"9":[["finn",{"fg":2}],["_",{"fg":7}],["air",{"fg":1}],[":",{"fg":7}],["~",{"fg":3}],["$ ",{"fg":7}],["cowsay Hallo Schn                                                                                                ",{}],["[master]",{"fg":3}],[" ",{}]]},"cursor":{"x":29}}],[0.084187,{"lines":{"9":[["finn",{"fg":2}],["_",{"fg":7}],["air",{"fg":1}],[":",{"fg":7}],["~",{"fg":3}],["$ ",{"fg":7}],["cowsay Hallo Sch                                                                                                 ",{}],["[master]",{"fg":3}],[" ",{}]]},"cursor":{"x":28}}],[0.08207299999999999,{"lines":{"9":[["finn",{"fg":2}],["_",{"fg":7}],["air",{"fg":1}],[":",{"fg":7}],["~",{"fg":3}],["$ ",{"fg":7}],["cowsay Hallo Sc                                                                                                  ",{}],["[master]",{"fg":3}],[" ",{}]]},"cursor":{"x":27}}],[0.0834,{"lines":{"9":[["finn",{"fg":2}],["_",{"fg":7}],["air",{"fg":1}],[":",{"fg":7}],["~",{"fg":3}],["$ ",{"fg":7}],["cowsay Hallo S                                                                                                   ",{}],["[master]",{"fg":3}],[" ",{}]]},"cursor":{"x":26}}],[0.083208,{"lines":{"9":[["finn",{"fg":2}],["_",{"fg":7}],["air",{"fg":1}],[":",{"fg":7}],["~",{"fg":3}],["$ ",{"fg":7}],["cowsay Hallo                                                                                                     ",{}],["[master]",{"fg":3}],[" ",{}]]},"cursor":{"x":25}}],[0.08365300000000001,{"cursor":{"x":24}}],[0.08340500000000001,{"lines":{"9":[["finn",{"fg":2}],["_",{"fg":7}],["air",{"fg":1}],[":",{"fg":7}],["~",{"fg":3}],["$ ",{"fg":7}],["cowsay Hall                                                                                                      ",{}],["[master]",{"fg":3}],[" ",{}]]},"cursor":{"x":23}}],[0.083803,{"lines":{"9":[["finn",{"fg":2}],["_",{"fg":7}],["air",{"fg":1}],[":",{"fg":7}],["~",{"fg":3}],["$ ",{"fg":7}],["cowsay Hal                                                                                                       ",{}],["[master]",{"fg":3}],[" ",{}]]},"cursor":{"x":22}}],[0.219662,{"lines":{"9":[["finn",{"fg":2}],["_",{"fg":7}],["air",{"fg":1}],[":",{"fg":7}],["~",{"fg":3}],["$ ",{"fg":7}],["cowsay Ha                                                                                                        ",{}],["[master]",{"fg":3}],[" ",{}]]},"cursor":{"x":21}}],[0.144199,{"lines":{"9":[["finn",{"fg":2}],["_",{"fg":7}],["air",{"fg":1}],[":",{"fg":7}],["~",{"fg":3}],["$ ",{"fg":7}],["cowsay H                                                                                                         ",{}],["[master]",{"fg":3}],[" ",{}]]},"cursor":{"x":20}}],[0.46388,{"lines":{"9":[["finn",{"fg":2}],["_",{"fg":7}],["air",{"fg":1}],[":",{"fg":7}],["~",{"fg":3}],["$ ",{"fg":7}],["cowsay                                                                                                           ",{}],["[master]",{"fg":3}],[" ",{}]]},"cursor":{"x":19}}],[0.4321,{"lines":{"9":[["finn",{"fg":2}],["_",{"fg":7}],["air",{"fg":1}],[":",{"fg":7}],["~",{"fg":3}],["$ ",{"fg":7}],["cowsay h                                                                                                         ",{}],["[master]",{"fg":3}],[" ",{}]]},"cursor":{"x":20}}],[0.072171,{"lines":{"9":[["finn",{"fg":2}],["_",{"fg":7}],["air",{"fg":1}],[":",{"fg":7}],["~",{"fg":3}],["$ ",{"fg":7}],["cowsay hi                                                                                                        ",{}],["[master]",{"fg":3}],[" ",{}]]},"cursor":{"x":21}}],[0.143834,{"lines":{"9":[["finn",{"fg":2}],["_",{"fg":7}],["air",{"fg":1}],[":",{"fg":7}],["~",{"fg":3}],["$ ",{"fg":7}],["cowsay hih                                                                                                       ",{}],["[master]",{"fg":3}],[" ",{}]]},"cursor":{"x":22}}],[0.064013,{"lines":{"9":[["finn",{"fg":2}],["_",{"fg":7}],["air",{"fg":1}],[":",{"fg":7}],["~",{"fg":3}],["$ ",{"fg":7}],["cowsay hihi                                                                                                      ",{}],["[master]",{"fg":3}],[" ",{}]]},"cursor":{"x":23}}],[0.5999409999999999,{"cursor":{"x":0,"y":10}}],[0.00113,{}],[0.033677,{"lines":{"10":[[" ______                                                                                                                               ",{}]],"11":[["< hihi >                                                                                                                              ",{}]],"12":[[" ------                                                                                                                               ",{}]],"13":[["        \\   ^__^                                                                                                                      ",{}]],"14":[["         \\  (oo)\\_______                                                                                                              ",{}]],"15":[["            (__)\\       )\\/\\                                                                                                          ",{}]],"16":[["                ||----w |                                                                                                             ",{}]],"17":[["                ||     ||                                                                                                             ",{}]]},"cursor":{"y":18}}],[0.009242999999999999,{"lines":{"18":[["finn",{"fg":2}],["_",{"fg":7}],["air",{"fg":1}],[":",{"fg":7}],["~",{"fg":3}],["$ ",{"fg":7}],["                                                                                                                 ",{}],["[master]",{"fg":3}],[" ",{}]]},"cursor":{"x":12}}],[1.692565,{"lines":{"18":[["finn",{"fg":2}],["_",{"fg":7}],["air",{"fg":1}],[":",{"fg":7}],["~",{"fg":3}],["$ ",{"fg":7}],["e                                                                                                                ",{}],["[master]",{"fg":3}],[" ",{}]]},"cursor":{"x":13}}],[0.255447,{"lines":{"18":[["finn",{"fg":2}],["_",{"fg":7}],["air",{"fg":1}],[":",{"fg":7}],["~",{"fg":3}],["$ ",{"fg":7}],["ex                                                                                                               ",{}],["[master]",{"fg":3}],[" ",{}]]},"cursor":{"x":14}}],[0.151903,{"lines":{"18":[["finn",{"fg":2}],["_",{"fg":7}],["air",{"fg":1}],[":",{"fg":7}],["~",{"fg":3}],["$ ",{"fg":7}],["exi                                                                                                              ",{}],["[master]",{"fg":3}],[" ",{}]]},"cursor":{"x":15}}],[0.167069,{"lines":{"18":[["finn",{"fg":2}],["_",{"fg":7}],["air",{"fg":1}],[":",{"fg":7}],["~",{"fg":3}],["$ ",{"fg":7}],["exit                                                                                                             ",{}],["[master]",{"fg":3}],[" ",{}]]},"cursor":{"x":16}}],[0.361621,{}],[0.001288,{"cursor":{"x":0,"y":19}}]]